bboxconverter/__init__.py
bboxconverter/core/__init__.py
bboxconverter/core/bbox.py
bboxconverter/core/bbox_parser.py
bboxconverter/io/__init__.py
bboxconverter/io/api.py
bboxconverter/io/reader_coco.py
bboxconverter/io/reader_csv.py
bboxconverter/io/reader_manifest.py
bboxconverter/io/reader_parquet.py
bboxconverter/io/reader_pascal_voc.py
bboxconverter/io/reader_xml.py
bboxconverter/io/reader_yolo.py
bboxconverter/io/writer_coco.py
bboxconverter/io/writer_json_lines.py
bboxconverter/io/writer_pascal_voc.py
bboxconverter/io/writer_yolo.py
bboxconverter-0.1.9.dist-info/LICENSE
bboxconverter-0.1.9.dist-info/METADATA
bboxconverter-0.1.9.dist-info/WHEEL
bboxconverter-0.1.9.dist-info/RECORD
