Metadata-Version: 2.1
Name: bboxconverter
Version: 0.1.9
Summary: Converting bounding box annotations to popular formats like a breeze.
License: GLP-3.0
Keywords: bbox converter,bbox,converter,bounding box,annotation,coco,yolo,voc,object detection,bboxtools,bboxutils,train,test,split
Author: Olivier D'Ancona
Author-email: olivier_dancona@hotmail.com
Requires-Python: >=3.8
Classifier: Development Status :: 3 - Alpha
Classifier: Intended Audience :: Developers
Classifier: Intended Audience :: Science/Research
Classifier: License :: OSI Approved :: MIT License
Classifier: License :: Other/Proprietary License
Classifier: Programming Language :: Python :: 3
Classifier: Programming Language :: Python :: 3.8
Classifier: Programming Language :: Python :: 3.9
Classifier: Programming Language :: Python :: 3.10
Classifier: Programming Language :: Python :: 3.11
Classifier: Topic :: Scientific/Engineering :: Artificial Intelligence
Requires-Dist: lxml (>=4.9.2,<5.0.0)
Requires-Dist: pandas (>=1.5.2,<2.0.0)
Requires-Dist: scikit-learn (>=1.2.1,<2.0.0)
Project-URL: documentation, https://bboxconverter.readthedocs.io/en/latest/index.html
Project-URL: repository, https://github.com/ODAncona/bboxconverter.git
